vnnews/__init__.py
vnnews/news_capture.py
vnnews/util.py
vnnews-0.0.1.dist-info/LICENSE
vnnews-0.0.1.dist-info/METADATA
vnnews-0.0.1.dist-info/WHEEL
vnnews-0.0.1.dist-info/top_level.txt
vnnews-0.0.1.dist-info/RECORD
