Metadata-Version: 2.1
Name: vnnews
Version: 0.0.1
Summary: A Python package that helps crawl updates from top Vietnamese news providers.
Home-page: https://github.com/thinh-vu/vnnews
Author: Thinh Vu
Author-email: mrthinh@live.com
Classifier: Programming Language :: Python :: 3
Classifier: License :: OSI Approved :: MIT License
Classifier: Operating System :: OS Independent
Requires-Python: >=3.7
License-File: LICENSE
Requires-Dist: urllib3
Requires-Dist: beautifulsoup4
